[
  { "id": "invictus", "date": "17-01-2023", "usd": 13.8239185326 },
  { "id": "invictus", "date": "16-01-2023", "usd": 13.5594197734 },
  { "id": "invictus", "date": "15-01-2023", "usd": 13.6466208209 },
  { "id": "invictus", "date": "14-01-2023", "usd": 13.8448345482 },
  { "id": "invictus", "date": "13-01-2023", "usd": 13.6971234113 },
  { "id": "invictus", "date": "12-01-2023", "usd": 14.1022235649 },
  { "id": "invictus", "date": "11-01-2023", "usd": 15.1594887641 },
  { "id": "invictus", "date": "10-01-2023", "usd": 15.1547573141 },
  { "id": "invictus", "date": "09-01-2023", "usd": 16.1065462385 },
  { "id": "invictus", "date": "08-01-2023", "usd": 16.0897984837 },
  { "id": "invictus", "date": "07-01-2023", "usd": 19.5590898741 },
  { "id": "invictus", "date": "06-01-2023", "usd": 19.5602153308 },
  { "id": "invictus", "date": "05-01-2023", "usd": 19.5600883746 },
  { "id": "invictus", "date": "04-01-2023", "usd": 20.9695385886 },
  { "id": "invictus", "date": "03-01-2023", "usd": 10.007560793 },
  { "id": "invictus", "date": "02-01-2023", "usd": 24.278435893 },
  { "id": "invictus", "date": "01-01-2023", "usd": 23.7123387968 },
  { "id": "invictus", "date": "31-12-2022", "usd": 37.2466947912 },
  { "id": "invictus", "date": "30-12-2022", "usd": 37.2531725727 },
  { "id": "invictus", "date": "29-12-2022", "usd": 37.2531145065 },
  { "id": "invictus", "date": "28-12-2022", "usd": 32.9250126754 },
  { "id": "invictus", "date": "27-12-2022", "usd": 36.2818861757 },
  { "id": "invictus", "date": "26-12-2022", "usd": 37.463211258 },
  { "id": "invictus", "date": "25-12-2022", "usd": 37.8996050653 },
  { "id": "invictus", "date": "24-12-2022", "usd": 26.8885937113 },
  { "id": "invictus", "date": "23-12-2022", "usd": 27.2151807826 },
  { "id": "invictus", "date": "22-12-2022", "usd": 27.2180913318 },
  { "id": "invictus", "date": "21-12-2022", "usd": 27.2159178878 },
  { "id": "invictus", "date": "20-12-2022", "usd": 27.2144790816 },
  { "id": "invictus", "date": "19-12-2022", "usd": 27.9782733288 },
  { "id": "invictus", "date": "18-12-2022", "usd": 28.0995742738 },
  { "id": "invictus", "date": "17-12-2022", "usd": 36.1993044595 },
  { "id": "invictus", "date": "16-12-2022", "usd": 32.8224187279 },
  { "id": "invictus", "date": "15-12-2022", "usd": 32.8260387653 },
  { "id": "invictus", "date": "14-12-2022", "usd": 33.2622980976 },
  { "id": "invictus", "date": "13-12-2022", "usd": 34.0181660579 },
  { "id": "invictus", "date": "12-12-2022", "usd": 34.0168221709 },
  { "id": "invictus", "date": "11-12-2022", "usd": 34.0134657593 },
  { "id": "invictus", "date": "10-12-2022", "usd": 34.0159154996 },
  { "id": "invictus", "date": "09-12-2022", "usd": 34.0137895404 },
  { "id": "invictus", "date": "08-12-2022", "usd": 34.0136335706 },
  { "id": "invictus", "date": "07-12-2022", "usd": 34.0136787474 },
  { "id": "invictus", "date": "06-12-2022", "usd": 35.0905208833 },
  { "id": "invictus", "date": "05-12-2022", "usd": 35.0868466804 },
  { "id": "invictus", "date": "04-12-2022", "usd": 32.6959370327 },
  { "id": "invictus", "date": "03-12-2022", "usd": 37.8899083578 },
  { "id": "invictus", "date": "02-12-2022", "usd": 34.3396316334 },
  { "id": "invictus", "date": "01-12-2022", "usd": 35.3600369424 },
  { "id": "invictus", "date": "30-11-2022", "usd": 37.8538373465 },
  { "id": "invictus", "date": "29-11-2022", "usd": 37.5832214568 },
  { "id": "invictus", "date": "28-11-2022", "usd": 37.9194518724 },
  { "id": "invictus", "date": "27-11-2022", "usd": 37.9165368421 },
  { "id": "invictus", "date": "26-11-2022", "usd": 37.9161247013 },
  { "id": "invictus", "date": "25-11-2022", "usd": 37.9129271836 },
  { "id": "invictus", "date": "24-11-2022", "usd": 36.8314986246 },
  { "id": "invictus", "date": "23-11-2022", "usd": 29.329455109 },
  { "id": "invictus", "date": "22-11-2022", "usd": 30.2886109938 },
  { "id": "invictus", "date": "21-11-2022", "usd": 34.4910367321 },
  { "id": "invictus", "date": "20-11-2022", "usd": 34.4895848549 },
  { "id": "invictus", "date": "19-11-2022", "usd": 37.9275839755 },
  { "id": "invictus", "date": "18-11-2022", "usd": 37.6075291526 },
  { "id": "invictus", "date": "17-11-2022", "usd": 37.9290747239 },
  { "id": "invictus", "date": "16-11-2022", "usd": 37.9305711342 },
  { "id": "invictus", "date": "15-11-2022", "usd": 36.8143662988 },
  { "id": "invictus", "date": "14-11-2022", "usd": 36.8240113426 },
  { "id": "invictus", "date": "13-11-2022", "usd": 38.31529014 },
  { "id": "invictus", "date": "12-11-2022", "usd": 37.7080446004 },
  { "id": "invictus", "date": "11-11-2022", "usd": 38.5091631484 },
  { "id": "invictus", "date": "10-11-2022", "usd": 37.9225205829 },
  { "id": "invictus", "date": "09-11-2022", "usd": 32.7537994405 },
  { "id": "invictus", "date": "08-11-2022", "usd": 30.5165773857 },
  { "id": "invictus", "date": "07-11-2022", "usd": 30.5216167664 },
  { "id": "invictus", "date": "06-11-2022", "usd": 34.3042649091 },
  { "id": "invictus", "date": "05-11-2022", "usd": 34.3062293713 },
  { "id": "invictus", "date": "04-11-2022", "usd": 34.3100126922 },
  { "id": "invictus", "date": "03-11-2022", "usd": 37.9490129262 },
  { "id": "invictus", "date": "02-11-2022", "usd": 37.9525362191 },
  { "id": "invictus", "date": "01-11-2022", "usd": 37.9070450309 },
  { "id": "invictus", "date": "31-10-2022", "usd": 38.0495934675 },
  { "id": "invictus", "date": "30-10-2022", "usd": 38.0523897587 },
  { "id": "invictus", "date": "29-10-2022", "usd": 38.051113615 },
  { "id": "invictus", "date": "28-10-2022", "usd": 38.0459994059 },
  { "id": "invictus", "date": "27-10-2022", "usd": 38.0473225626 },
  { "id": "invictus", "date": "26-10-2022", "usd": 38.0499741348 },
  { "id": "invictus", "date": "25-10-2022", "usd": 38.0463171775 },
  { "id": "invictus", "date": "24-10-2022", "usd": 38.046929946 },
  { "id": "invictus", "date": "23-10-2022", "usd": 38.0521780046 },
  { "id": "invictus", "date": "22-10-2022", "usd": 38.0500027854 },
  { "id": "invictus", "date": "21-10-2022", "usd": 38.0498637284 },
  { "id": "invictus", "date": "20-10-2022", "usd": 38.1445562436 },
  { "id": "invictus", "date": "19-10-2022", "usd": 38.1465923869 },
  { "id": "invictus", "date": "18-10-2022", "usd": 38.1482556248 },
  { "id": "invictus", "date": "17-10-2022", "usd": 38.0513881234 },
  { "id": "invictus", "date": "16-10-2022", "usd": 38.1265139741 },
  { "id": "invictus", "date": "15-10-2022", "usd": 38.1553463227 },
  { "id": "invictus", "date": "14-10-2022", "usd": 38.1587703679 },
  { "id": "invictus", "date": "13-10-2022", "usd": 38.15929881 },
  { "id": "invictus", "date": "12-10-2022", "usd": 38.1830536285 },
  { "id": "invictus", "date": "11-10-2022", "usd": 38.230967653 },
  { "id": "invictus", "date": "10-10-2022", "usd": 38.4495026168 },
  { "id": "invictus", "date": "09-10-2022", "usd": 37.8669427211 },
  { "id": "invictus", "date": "08-10-2022", "usd": 37.8732569844 },
  { "id": "invictus", "date": "07-10-2022", "usd": 37.8672896368 },
  { "id": "invictus", "date": "06-10-2022", "usd": 37.894851387 },
  { "id": "invictus", "date": "05-10-2022", "usd": 37.8955335515 },
  { "id": "invictus", "date": "04-10-2022", "usd": 37.9031790137 },
  { "id": "invictus", "date": "03-10-2022", "usd": 38.0794132309 },
  { "id": "invictus", "date": "02-10-2022", "usd": 37.9065395289 },
  { "id": "invictus", "date": "01-10-2022", "usd": 37.903411081 },
  { "id": "invictus", "date": "30-09-2022", "usd": 38.0359313329 },
  { "id": "invictus", "date": "29-09-2022", "usd": 37.8939010386 },
  { "id": "invictus", "date": "28-09-2022", "usd": 37.9080220701 },
  { "id": "invictus", "date": "27-09-2022", "usd": 37.9080444074 },
  { "id": "invictus", "date": "26-09-2022", "usd": 37.8486357466 },
  { "id": "invictus", "date": "25-09-2022", "usd": 37.8423974137 },
  { "id": "invictus", "date": "24-09-2022", "usd": 37.901099224 },
  { "id": "invictus", "date": "23-09-2022", "usd": 37.9041771607 },
  { "id": "invictus", "date": "22-09-2022", "usd": 37.9017562084 },
  { "id": "invictus", "date": "21-09-2022", "usd": 37.9090748143 },
  { "id": "invictus", "date": "20-09-2022", "usd": 37.887588327 },
  { "id": "invictus", "date": "19-09-2022", "usd": 37.9067340656 },
  { "id": "invictus", "date": "18-09-2022", "usd": 38.4058500513 },
  { "id": "invictus", "date": "17-09-2022", "usd": 38.3812830908 },
  { "id": "invictus", "date": "16-09-2022", "usd": 37.9070428177 },
  { "id": "invictus", "date": "15-09-2022", "usd": 37.8391289867 },
  { "id": "invictus", "date": "14-09-2022", "usd": 37.9802852256 },
  { "id": "invictus", "date": "13-09-2022", "usd": 37.8382163737 },
  { "id": "invictus", "date": "12-09-2022", "usd": 37.8701505589 },
  { "id": "invictus", "date": "11-09-2022", "usd": 37.9041149484 },
  { "id": "invictus", "date": "10-09-2022", "usd": 38.0631465654 },
  { "id": "invictus", "date": "09-09-2022", "usd": 38.0663548956 },
  { "id": "invictus", "date": "08-09-2022", "usd": 38.1879349702 },
  { "id": "invictus", "date": "07-09-2022", "usd": 38.1902315428 },
  { "id": "invictus", "date": "06-09-2022", "usd": 38.1723041929 },
  { "id": "invictus", "date": "05-09-2022", "usd": 37.8476507181 },
  { "id": "invictus", "date": "04-09-2022", "usd": 37.9022132196 },
  { "id": "invictus", "date": "03-09-2022", "usd": 37.9094031548 },
  { "id": "invictus", "date": "02-09-2022", "usd": 38.1626784453 },
  { "id": "invictus", "date": "01-09-2022", "usd": 38.2131554574 },
  { "id": "invictus", "date": "31-08-2022", "usd": 37.8520885999 },
  { "id": "invictus", "date": "30-08-2022", "usd": 37.8523783002 },
  { "id": "invictus", "date": "29-08-2022", "usd": 37.8572122882 },
  { "id": "invictus", "date": "28-08-2022", "usd": 37.9031996398 },
  { "id": "invictus", "date": "27-08-2022", "usd": 38.0861812592 },
  { "id": "invictus", "date": "26-08-2022", "usd": 37.9379100389 },
  { "id": "invictus", "date": "25-08-2022", "usd": 38.228727511 },
  { "id": "invictus", "date": "24-08-2022", "usd": 38.0785288228 },
  { "id": "invictus", "date": "23-08-2022", "usd": 38.0829544901 },
  { "id": "invictus", "date": "22-08-2022", "usd": 38.0554378885 },
  { "id": "invictus", "date": "21-08-2022", "usd": 38.1704764925 },
  { "id": "invictus", "date": "20-08-2022", "usd": 38.0103576015 },
  { "id": "invictus", "date": "19-08-2022", "usd": 38.0048853447 },
  { "id": "invictus", "date": "18-08-2022", "usd": 38.1008045934 },
  { "id": "invictus", "date": "17-08-2022", "usd": 37.8973458598 },
  { "id": "invictus", "date": "16-08-2022", "usd": 38.0099426941 },
  { "id": "invictus", "date": "15-08-2022", "usd": 38.2052225746 },
  { "id": "invictus", "date": "14-08-2022", "usd": 37.5891276744 },
  { "id": "invictus", "date": "13-08-2022", "usd": 38.1391159174 },
  { "id": "invictus", "date": "12-08-2022", "usd": 37.8779190113 },
  { "id": "invictus", "date": "11-08-2022", "usd": 37.8633484421 },
  { "id": "invictus", "date": "10-08-2022", "usd": 37.946385056 },
  { "id": "invictus", "date": "09-08-2022", "usd": 37.8394149574 },
  { "id": "invictus", "date": "08-08-2022", "usd": 37.8219020489 },
  { "id": "invictus", "date": "07-08-2022", "usd": 37.7300752754 },
  { "id": "invictus", "date": "06-08-2022", "usd": 37.9293638741 },
  { "id": "invictus", "date": "05-08-2022", "usd": 38.8012571892 },
  { "id": "invictus", "date": "04-08-2022", "usd": 37.7523849509 },
  { "id": "invictus", "date": "03-08-2022", "usd": 37.8233206126 },
  { "id": "invictus", "date": "02-08-2022", "usd": 37.6486924744 },
  { "id": "invictus", "date": "01-08-2022", "usd": 37.8116848683 },
  { "id": "invictus", "date": "31-07-2022", "usd": 37.5586387445 },
  { "id": "invictus", "date": "30-07-2022", "usd": 37.6463184571 },
  { "id": "invictus", "date": "29-07-2022", "usd": 37.7913640521 },
  { "id": "invictus", "date": "28-07-2022", "usd": 37.8078354402 },
  { "id": "invictus", "date": "27-07-2022", "usd": 37.8582536018 },
  { "id": "invictus", "date": "26-07-2022", "usd": 37.4545629718 },
  { "id": "invictus", "date": "25-07-2022", "usd": 37.896815009 },
  { "id": "invictus", "date": "24-07-2022", "usd": 37.7943705171 },
  { "id": "invictus", "date": "23-07-2022", "usd": 37.838540441 },
  { "id": "invictus", "date": "22-07-2022", "usd": 38.0208856973 },
  { "id": "invictus", "date": "21-07-2022", "usd": 38.2865450031 },
  { "id": "invictus", "date": "20-07-2022", "usd": 38.3944286164 },
  { "id": "invictus", "date": "19-07-2022", "usd": 38.1299108409 },
  { "id": "invictus", "date": "18-07-2022", "usd": 39.0696923917 },
  { "id": "invictus", "date": "17-07-2022", "usd": 38.2191716458 },
  { "id": "invictus", "date": "16-07-2022", "usd": 37.7798064491 },
  { "id": "invictus", "date": "15-07-2022", "usd": 38.1532796609 },
  { "id": "invictus", "date": "14-07-2022", "usd": 37.6754508154 },
  { "id": "invictus", "date": "13-07-2022", "usd": 37.7387233518 },
  { "id": "invictus", "date": "12-07-2022", "usd": 37.6686211058 },
  { "id": "invictus", "date": "11-07-2022", "usd": 37.9215305461 },
  { "id": "invictus", "date": "10-07-2022", "usd": 37.7403406296 },
  { "id": "invictus", "date": "09-07-2022", "usd": 37.8872380591 },
  { "id": "invictus", "date": "08-07-2022", "usd": 37.3803688378 },
  { "id": "invictus", "date": "07-07-2022", "usd": 37.6785318324 },
  { "id": "invictus", "date": "06-07-2022", "usd": 37.0691204545 },
  { "id": "invictus", "date": "05-07-2022", "usd": 37.0815042816 },
  { "id": "invictus", "date": "04-07-2022", "usd": 37.6227114531 },
  { "id": "invictus", "date": "03-07-2022", "usd": 37.5927762836 },
  { "id": "invictus", "date": "02-07-2022", "usd": 37.9566534309 },
  { "id": "invictus", "date": "01-07-2022", "usd": 37.9124488145 },
  { "id": "invictus", "date": "30-06-2022", "usd": 37.907664319 },
  { "id": "invictus", "date": "29-06-2022", "usd": 37.9182567232 },
  { "id": "invictus", "date": "28-06-2022", "usd": 37.9097805358 },
  { "id": "invictus", "date": "27-06-2022", "usd": 37.8681622197 },
  { "id": "invictus", "date": "26-06-2022", "usd": 37.9750821736 },
  { "id": "invictus", "date": "25-06-2022", "usd": 37.8928074484 },
  { "id": "invictus", "date": "24-06-2022", "usd": 38.277641404 },
  { "id": "invictus", "date": "23-06-2022", "usd": 38.0443071516 },
  { "id": "invictus", "date": "22-06-2022", "usd": 38.087223524 },
  { "id": "invictus", "date": "21-06-2022", "usd": 37.9038735033 },
  { "id": "invictus", "date": "20-06-2022", "usd": 37.7763266836 },
  { "id": "invictus", "date": "19-06-2022", "usd": 37.9014495939 },
  { "id": "invictus", "date": "18-06-2022", "usd": 38.0159891104 },
  { "id": "invictus", "date": "17-06-2022", "usd": 37.9596039198 },
  { "id": "invictus", "date": "16-06-2022", "usd": 38.1081309019 },
  { "id": "invictus", "date": "15-06-2022", "usd": 38.1704436439 },
  { "id": "invictus", "date": "14-06-2022", "usd": 37.933294501 },
  { "id": "invictus", "date": "13-06-2022", "usd": 37.5687681371 },
  { "id": "invictus", "date": "12-06-2022", "usd": 37.6422018446 },
  { "id": "invictus", "date": "11-06-2022", "usd": 37.6806956452 },
  { "id": "invictus", "date": "10-06-2022", "usd": 37.7989821794 },
  { "id": "invictus", "date": "09-06-2022", "usd": 37.6728520337 },
  { "id": "invictus", "date": "08-06-2022", "usd": 37.1521005395 },
  { "id": "invictus", "date": "07-06-2022", "usd": 37.7918612023 },
  { "id": "invictus", "date": "06-06-2022", "usd": 38.0224594098 },
  { "id": "invictus", "date": "05-06-2022", "usd": 37.8632743121 },
  { "id": "invictus", "date": "04-06-2022", "usd": 38.2528070083 },
  { "id": "invictus", "date": "03-06-2022", "usd": 37.5838972724 },
  { "id": "invictus", "date": "02-06-2022", "usd": 37.0801892814 },
  { "id": "invictus", "date": "01-06-2022", "usd": 38.5185453312 },
  { "id": "invictus", "date": "31-05-2022", "usd": 38.0019018928 },
  { "id": "invictus", "date": "30-05-2022", "usd": 38.0755727817 },
  { "id": "invictus", "date": "29-05-2022", "usd": 38.0884670945 },
  { "id": "invictus", "date": "28-05-2022", "usd": 38.3364487528 },
  { "id": "invictus", "date": "27-05-2022", "usd": 38.0146145968 },
  { "id": "invictus", "date": "26-05-2022", "usd": 38.8474104972 },
  { "id": "invictus", "date": "25-05-2022", "usd": 37.872494889 },
  { "id": "invictus", "date": "24-05-2022", "usd": 38.0451843059 },
  { "id": "invictus", "date": "23-05-2022", "usd": 37.8852583149 },
  { "id": "invictus", "date": "22-05-2022", "usd": 37.8464807793 },
  { "id": "invictus", "date": "21-05-2022", "usd": 37.8727188271 },
  { "id": "invictus", "date": "20-05-2022", "usd": 37.9047117 },
  { "id": "invictus", "date": "19-05-2022", "usd": 36.9250340688 },
  { "id": "invictus", "date": "18-05-2022", "usd": 37.0410304234 },
  { "id": "invictus", "date": "17-05-2022", "usd": 39.9288839474 },
  { "id": "invictus", "date": "16-05-2022", "usd": 37.9161845001 },
  { "id": "invictus", "date": "15-05-2022", "usd": 41.202175742 },
  { "id": "invictus", "date": "14-05-2022", "usd": 37.8726984323 },
  { "id": "invictus", "date": "13-05-2022", "usd": 37.8877993177 },
  { "id": "invictus", "date": "12-05-2022", "usd": 37.9178354631 },
  { "id": "invictus", "date": "11-05-2022", "usd": 37.9321461395 },
  { "id": "invictus", "date": "10-05-2022", "usd": 37.8968340874 },
  { "id": "invictus", "date": "09-05-2022", "usd": 37.8650685722 },
  { "id": "invictus", "date": "08-05-2022", "usd": 37.8676105588 },
  { "id": "invictus", "date": "07-05-2022", "usd": 37.8597433028 },
  { "id": "invictus", "date": "06-05-2022", "usd": 37.8611034116 },
  { "id": "invictus", "date": "05-05-2022", "usd": 37.8865817899 },
  { "id": "invictus", "date": "04-05-2022", "usd": 37.8423886452 },
  { "id": "invictus", "date": "03-05-2022", "usd": 37.9092495592 },
  { "id": "invictus", "date": "02-05-2022", "usd": 37.9069658858 },
  { "id": "invictus", "date": "01-05-2022", "usd": 37.9186236226 },
  { "id": "invictus", "date": "30-04-2022", "usd": 37.7615471476 },
  { "id": "invictus", "date": "29-04-2022", "usd": 38.1224842778 },
  { "id": "invictus", "date": "28-04-2022", "usd": 37.90487006 },
  { "id": "invictus", "date": "27-04-2022", "usd": 37.8784922557 },
  { "id": "invictus", "date": "26-04-2022", "usd": 37.9105924377 },
  { "id": "invictus", "date": "25-04-2022", "usd": 37.8649267219 },
  { "id": "invictus", "date": "24-04-2022", "usd": 37.8544957254 },
  { "id": "invictus", "date": "23-04-2022", "usd": 37.8813587821 },
  { "id": "invictus", "date": "22-04-2022", "usd": 37.8983563508 },
  { "id": "invictus", "date": "21-04-2022", "usd": 37.8791887029 },
  { "id": "invictus", "date": "20-04-2022", "usd": 37.8094051538 },
  { "id": "invictus", "date": "19-04-2022", "usd": 37.8734098803 },
  { "id": "invictus", "date": "18-04-2022", "usd": 37.914649836 },
  { "id": "invictus", "date": "17-04-2022", "usd": 37.8857406673 },
  { "id": "invictus", "date": "16-04-2022", "usd": 37.8893769439 },
  { "id": "invictus", "date": "15-04-2022", "usd": 37.9108493573 },
  { "id": "invictus", "date": "14-04-2022", "usd": 37.8768517163 },
  { "id": "invictus", "date": "13-04-2022", "usd": 37.8945491019 },
  { "id": "invictus", "date": "12-04-2022", "usd": 37.8730862547 },
  { "id": "invictus", "date": "11-04-2022", "usd": 37.8510926988 },
  { "id": "invictus", "date": "10-04-2022", "usd": 37.8699184602 },
  { "id": "invictus", "date": "09-04-2022", "usd": 37.9136822052 },
  { "id": "invictus", "date": "08-04-2022", "usd": 37.8999747776 },
  { "id": "invictus", "date": "07-04-2022", "usd": 37.9125343763 },
  { "id": "invictus", "date": "06-04-2022", "usd": 37.890308283 },
  { "id": "invictus", "date": "05-04-2022", "usd": 37.8539800156 },
  { "id": "invictus", "date": "04-04-2022", "usd": 37.9106721453 },
  { "id": "invictus", "date": "03-04-2022", "usd": 37.869476111 },
  { "id": "invictus", "date": "02-04-2022", "usd": 37.8635260506 },
  { "id": "invictus", "date": "01-04-2022", "usd": 37.8837319587 },
  { "id": "invictus", "date": "31-03-2022", "usd": 37.9496148752 },
  { "id": "invictus", "date": "30-03-2022", "usd": 37.8353136433 },
  { "id": "invictus", "date": "29-03-2022", "usd": 37.9523541929 },
  { "id": "invictus", "date": "28-03-2022", "usd": 37.9078436275 },
  { "id": "invictus", "date": "27-03-2022", "usd": 37.9382265295 },
  { "id": "invictus", "date": "26-03-2022", "usd": 38.0394273434 },
  { "id": "invictus", "date": "25-03-2022", "usd": 38.0497660069 },
  { "id": "invictus", "date": "24-03-2022", "usd": 37.8938164796 },
  { "id": "invictus", "date": "23-03-2022", "usd": 38.0075766935 },
  { "id": "invictus", "date": "22-03-2022", "usd": 37.9011058384 },
  { "id": "invictus", "date": "21-03-2022", "usd": 37.8976172965 },
  { "id": "invictus", "date": "20-03-2022", "usd": 35.3747220273 },
  { "id": "invictus", "date": "19-03-2022", "usd": 35.2010707506 },
  { "id": "invictus", "date": "18-03-2022", "usd": 34.2903277307 },
  { "id": "invictus", "date": "17-03-2022", "usd": 32.2593436191 },
  { "id": "invictus", "date": "16-03-2022", "usd": 31.5468715659 },
  { "id": "invictus", "date": "15-03-2022", "usd": 33.8565956905 },
  { "id": "invictus", "date": "14-03-2022", "usd": 33.1395557154 },
  { "id": "invictus", "date": "13-03-2022", "usd": 34.4889748357 },
  { "id": "invictus", "date": "12-03-2022", "usd": 32.4560941211 },
  { "id": "invictus", "date": "11-03-2022", "usd": 31.4399410703 },
  { "id": "invictus", "date": "10-03-2022", "usd": 34.7945510103 },
  { "id": "invictus", "date": "09-03-2022", "usd": 35.378189984 },
  { "id": "invictus", "date": "08-03-2022", "usd": 35.0286336326 },
  { "id": "invictus", "date": "07-03-2022", "usd": 38.2051589347 },
  { "id": "invictus", "date": "06-03-2022", "usd": 38.7981613282 },
  { "id": "invictus", "date": "05-03-2022", "usd": 42.0085812753 },
  { "id": "invictus", "date": "04-03-2022", "usd": 42.923553867 },
  { "id": "invictus", "date": "03-03-2022", "usd": 44.1625145639 },
  { "id": "invictus", "date": "02-03-2022", "usd": 44.3922882754 },
  { "id": "invictus", "date": "01-03-2022", "usd": 44.4470740495 },
  { "id": "invictus", "date": "28-02-2022", "usd": 44.8386969702 },
  { "id": "invictus", "date": "27-02-2022", "usd": 46.8306579883 },
  { "id": "invictus", "date": "26-02-2022", "usd": 48.4359908072 },
  { "id": "invictus", "date": "25-02-2022", "usd": 48.1667099415 },
  { "id": "invictus", "date": "24-02-2022", "usd": 48.2553052908 },
  { "id": "invictus", "date": "23-02-2022", "usd": 50.9764137266 },
  { "id": "invictus", "date": "22-02-2022", "usd": 51.5975377867 },
  { "id": "invictus", "date": "21-02-2022", "usd": 57.5910232854 },
  { "id": "invictus", "date": "20-02-2022", "usd": 64.8567446222 },
  { "id": "invictus", "date": "19-02-2022", "usd": 66.0567651273 },
  { "id": "invictus", "date": "18-02-2022", "usd": 67.618230973 },
  { "id": "invictus", "date": "17-02-2022", "usd": 68.0293810554 },
  { "id": "invictus", "date": "16-02-2022", "usd": 69.2843770297 },
  { "id": "invictus", "date": "15-02-2022", "usd": 73.1487176334 },
  { "id": "invictus", "date": "14-02-2022", "usd": 73.0116133252 },
  { "id": "invictus", "date": "13-02-2022", "usd": 82.2393617576 },
  { "id": "invictus", "date": "12-02-2022", "usd": 86.9463614476 },
  { "id": "invictus", "date": "11-02-2022", "usd": 76.2992888775 },
  { "id": "invictus", "date": "10-02-2022", "usd": 78.8025387335 },
  { "id": "invictus", "date": "09-02-2022", "usd": 78.7071905776 },
  { "id": "invictus", "date": "08-02-2022", "usd": 78.9504764722 },
  { "id": "invictus", "date": "07-02-2022", "usd": 66.0174159043 },
  { "id": "invictus", "date": "06-02-2022", "usd": 64.8022799363 },
  { "id": "invictus", "date": "05-02-2022", "usd": 64.4288730304 },
  { "id": "invictus", "date": "04-02-2022", "usd": 64.4105606259 },
  { "id": "invictus", "date": "03-02-2022", "usd": 63.6603150853 },
  { "id": "invictus", "date": "02-02-2022", "usd": 63.4583622636 },
  { "id": "invictus", "date": "01-02-2022", "usd": 63.5063239669 },
  { "id": "invictus", "date": "31-01-2022", "usd": 62.6910734911 },
  { "id": "invictus", "date": "30-01-2022", "usd": 67.6063367769 },
  { "id": "invictus", "date": "29-01-2022", "usd": 65.3043356599 },
  { "id": "invictus", "date": "28-01-2022", "usd": 59.7723517464 },
  { "id": "invictus", "date": "27-01-2022", "usd": 58.9005059745 },
  { "id": "invictus", "date": "26-01-2022", "usd": 59.519016879 },
  { "id": "invictus", "date": "25-01-2022", "usd": 63.7114326413 },
  { "id": "invictus", "date": "24-01-2022", "usd": 62.4788080651 },
  { "id": "invictus", "date": "23-01-2022", "usd": 70.3008788723 },
  { "id": "invictus", "date": "22-01-2022", "usd": 74.8449886138 },
  { "id": "invictus", "date": "21-01-2022", "usd": 72.1906296019 },
  { "id": "invictus", "date": "20-01-2022", "usd": 83.094980482 },
  { "id": "invictus", "date": "19-01-2022", "usd": 87.9794921041 },
  { "id": "invictus", "date": "18-01-2022", "usd": 90.7234668357 },
  { "id": "invictus", "date": "17-01-2022", "usd": 114.1486374875 },
  { "id": "invictus", "date": "16-01-2022", "usd": 116.8853212342 },
  { "id": "invictus", "date": "15-01-2022", "usd": 138.070459331 },
  { "id": "invictus", "date": "14-01-2022", "usd": 161.1781280348 },
  { "id": "invictus", "date": "13-01-2022", "usd": 170.1280604461 },
  { "id": "invictus", "date": "12-01-2022", "usd": 185.5399438472 },
  { "id": "invictus", "date": "11-01-2022", "usd": 208.4005233538 },
  { "id": "invictus", "date": "10-01-2022", "usd": 230.2505813634 },
  { "id": "invictus", "date": "09-01-2022", "usd": 257.2450972871 },
  { "id": "invictus", "date": "08-01-2022", "usd": 253.4351931236 },
  { "id": "invictus", "date": "07-01-2022", "usd": 250.1241307782 },
  { "id": "invictus", "date": "06-01-2022", "usd": 263.6318981522 },
  { "id": "invictus", "date": "05-01-2022", "usd": 260.1981425896 },
  { "id": "invictus", "date": "04-01-2022", "usd": 266.7428828122 },
  { "id": "invictus", "date": "03-01-2022", "usd": 235.5101915479 },
  { "id": "invictus", "date": "02-01-2022", "usd": 269.1067583635 },
  { "id": "invictus", "date": "01-01-2022", "usd": 277.7967654015 },
  { "id": "invictus", "date": "31-12-2021", "usd": 274.5993541749 },
  { "id": "invictus", "date": "30-12-2021", "usd": 272.6770850369 },
  { "id": "invictus", "date": "29-12-2021", "usd": 268.2852775397 },
  { "id": "invictus", "date": "28-12-2021", "usd": 256.4631744371 },
  { "id": "invictus", "date": "27-12-2021", "usd": 280.2745369401 },
  { "id": "invictus", "date": "26-12-2021", "usd": 304.5824239294 },
  { "id": "invictus", "date": "25-12-2021", "usd": 326.4211929137 },
  { "id": "invictus", "date": "24-12-2021", "usd": 316.3048194792 },
  { "id": "invictus", "date": "23-12-2021", "usd": 364.3667210727 },
  { "id": "invictus", "date": "22-12-2021", "usd": 396.2376373612 },
  { "id": "invictus", "date": "21-12-2021", "usd": 376.003530744 },
  { "id": "invictus", "date": "20-12-2021", "usd": 325.4955927972 },
  { "id": "invictus", "date": "19-12-2021", "usd": 308.732327972 },
  { "id": "invictus", "date": "18-12-2021", "usd": 287.4773971974 },
  { "id": "invictus", "date": "17-12-2021", "usd": 267.6861890533 },
  { "id": "invictus", "date": "16-12-2021", "usd": 256.7809487669 },
  { "id": "invictus", "date": "15-12-2021", "usd": 257.0434591197 },
  { "id": "invictus", "date": "14-12-2021", "usd": 236.4406842575 },
  { "id": "invictus", "date": "13-12-2021", "usd": 245.3949190075 },
  { "id": "invictus", "date": "12-12-2021", "usd": 304.5791629604 },
  { "id": "invictus", "date": "11-12-2021", "usd": 313.0599167186 },
  { "id": "invictus", "date": "10-12-2021", "usd": 356.0620775515 },
  { "id": "invictus", "date": "09-12-2021", "usd": 361.6729512637 },
  { "id": "invictus", "date": "08-12-2021", "usd": 334.1415727514 },
  { "id": "invictus", "date": "07-12-2021", "usd": 367.3916343535 },
  { "id": "invictus", "date": "06-12-2021", "usd": 379.6888272469 },
  { "id": "invictus", "date": "05-12-2021", "usd": 457.6845189461 },
  { "id": "invictus", "date": "04-12-2021", "usd": 458.046680077 },
  { "id": "invictus", "date": "03-12-2021", "usd": 529.7723860812 },
  { "id": "invictus", "date": "02-12-2021", "usd": 600.3475474657 },
  { "id": "invictus", "date": "01-12-2021", "usd": 746.4598588399 },
  { "id": "invictus", "date": "30-11-2021", "usd": 809.4152193989 },
  { "id": "invictus", "date": "29-11-2021", "usd": 792.8283508601 },
  { "id": "invictus", "date": "28-11-2021", "usd": 746.418035216 },
  { "id": "invictus", "date": "27-11-2021", "usd": 726.2379112085 },
  { "id": "invictus", "date": "26-11-2021", "usd": 797.908333101 },
  { "id": "invictus", "date": "25-11-2021", "usd": 986.6893687636 },
  { "id": "invictus", "date": "24-11-2021", "usd": 1072.0974718297 },
  { "id": "invictus", "date": "23-11-2021", "usd": 1362.1261031904 },
  { "id": "invictus", "date": "22-11-2021", "usd": 1304.5756977395 },
  { "id": "invictus", "date": "21-11-2021", "usd": 1087.2449484185 },
  { "id": "invictus", "date": "20-11-2021", "usd": 1277.5201442451 },
  { "id": "invictus", "date": "19-11-2021", "usd": 1137.4301113025 },
  { "id": "invictus", "date": "18-11-2021", "usd": 873.2841259973 },
  { "id": "invictus", "date": "17-11-2021", "usd": 952.5551972485 },
  { "id": "invictus", "date": "16-11-2021", "usd": 646.2110594503 },
  { "id": "invictus", "date": "15-11-2021", "usd": 392.8947460162 },
  { "id": "invictus", "date": "14-11-2021", "usd": 399.6117406539 },
  { "id": "invictus", "date": "13-11-2021", "usd": 373.489083522 },
  { "id": "invictus", "date": "12-11-2021", "usd": 422.0627550051 }
]
