[
  { "id": "mango-markets", "date": "16-01-2023", "usd": 0.0202218794 },
  { "id": "mango-markets", "date": "15-01-2023", "usd": 0.0199956674 },
  { "id": "mango-markets", "date": "14-01-2023", "usd": 0.0198420133 },
  { "id": "mango-markets", "date": "13-01-2023", "usd": 0.0196134185 },
  { "id": "mango-markets", "date": "12-01-2023", "usd": 0.0192633418 },
  { "id": "mango-markets", "date": "11-01-2023", "usd": 0.0191575132 },
  { "id": "mango-markets", "date": "10-01-2023", "usd": 0.0193822457 },
  { "id": "mango-markets", "date": "09-01-2023", "usd": 0.019541501 },
  { "id": "mango-markets", "date": "08-01-2023", "usd": 0.0199225613 },
  { "id": "mango-markets", "date": "07-01-2023", "usd": 0.0204638284 },
  { "id": "mango-markets", "date": "06-01-2023", "usd": 0.0202522735 },
  { "id": "mango-markets", "date": "05-01-2023", "usd": 0.0195249979 },
  { "id": "mango-markets", "date": "04-01-2023", "usd": 0.0197319514 },
  { "id": "mango-markets", "date": "03-01-2023", "usd": 0.0192767816 },
  { "id": "mango-markets", "date": "02-01-2023", "usd": 0.0184157844 },
  { "id": "mango-markets", "date": "01-01-2023", "usd": 0.0180621105 },
  { "id": "mango-markets", "date": "31-12-2022", "usd": 0.0190677393 },
  { "id": "mango-markets", "date": "30-12-2022", "usd": 0.0190059943 },
  { "id": "mango-markets", "date": "29-12-2022", "usd": 0.0195904183 },
  { "id": "mango-markets", "date": "28-12-2022", "usd": 0.0196737651 },
  { "id": "mango-markets", "date": "27-12-2022", "usd": 0.0204361363 },
  { "id": "mango-markets", "date": "26-12-2022", "usd": 0.0199098673 },
  { "id": "mango-markets", "date": "25-12-2022", "usd": 0.0202591076 },
  { "id": "mango-markets", "date": "24-12-2022", "usd": 0.0200448493 },
  { "id": "mango-markets", "date": "23-12-2022", "usd": 0.0206212395 },
  { "id": "mango-markets", "date": "22-12-2022", "usd": 0.0201646978 },
  { "id": "mango-markets", "date": "21-12-2022", "usd": 0.0205013542 },
  { "id": "mango-markets", "date": "20-12-2022", "usd": 0.0206375904 },
  { "id": "mango-markets", "date": "19-12-2022", "usd": 0.0205523646 },
  { "id": "mango-markets", "date": "18-12-2022", "usd": 0.0210664813 },
  { "id": "mango-markets", "date": "17-12-2022", "usd": 0.020991943 },
  { "id": "mango-markets", "date": "16-12-2022", "usd": 0.0215344844 },
  { "id": "mango-markets", "date": "15-12-2022", "usd": 0.0222387355 },
  { "id": "mango-markets", "date": "14-12-2022", "usd": 0.0227635127 },
  { "id": "mango-markets", "date": "13-12-2022", "usd": 0.023079128 },
  { "id": "mango-markets", "date": "12-12-2022", "usd": 0.0230757513 },
  { "id": "mango-markets", "date": "11-12-2022", "usd": 0.0254677872 },
  { "id": "mango-markets", "date": "10-12-2022", "usd": 0.0253309391 },
  { "id": "mango-markets", "date": "09-12-2022", "usd": 0.0246566118 },
  { "id": "mango-markets", "date": "08-12-2022", "usd": 0.0245499073 },
  { "id": "mango-markets", "date": "07-12-2022", "usd": 0.0257870584 },
  { "id": "mango-markets", "date": "06-12-2022", "usd": 0.0257145861 },
  { "id": "mango-markets", "date": "05-12-2022", "usd": 0.0258228103 },
  { "id": "mango-markets", "date": "04-12-2022", "usd": 0.0237164598 },
  { "id": "mango-markets", "date": "03-12-2022", "usd": 0.0224137557 },
  { "id": "mango-markets", "date": "02-12-2022", "usd": 0.0201850045 },
  { "id": "mango-markets", "date": "01-12-2022", "usd": 0.0202327339 },
  { "id": "mango-markets", "date": "30-11-2022", "usd": 0.0200525736 },
  { "id": "mango-markets", "date": "29-11-2022", "usd": 0.0202180685 },
  { "id": "mango-markets", "date": "28-11-2022", "usd": 0.0197828037 },
  { "id": "mango-markets", "date": "27-11-2022", "usd": 0.0196864561 },
  { "id": "mango-markets", "date": "26-11-2022", "usd": 0.0199969885 },
  { "id": "mango-markets", "date": "25-11-2022", "usd": 0.0199215421 },
  { "id": "mango-markets", "date": "24-11-2022", "usd": 0.0199798057 },
  { "id": "mango-markets", "date": "23-11-2022", "usd": 0.0198336541 },
  { "id": "mango-markets", "date": "22-11-2022", "usd": 0.0200072601 },
  { "id": "mango-markets", "date": "21-11-2022", "usd": 0.0196803929 },
  { "id": "mango-markets", "date": "20-11-2022", "usd": 0.0195813379 },
  { "id": "mango-markets", "date": "19-11-2022", "usd": 0.0153669734 },
  { "id": "mango-markets", "date": "18-11-2022", "usd": 0.0153343297 },
  { "id": "mango-markets", "date": "17-11-2022", "usd": 0.014959792 },
  { "id": "mango-markets", "date": "16-11-2022", "usd": 0.0158863745 },
  { "id": "mango-markets", "date": "15-11-2022", "usd": 0.013028768 },
  { "id": "mango-markets", "date": "14-11-2022", "usd": 0.0137207036 },
  { "id": "mango-markets", "date": "13-11-2022", "usd": 0.0161331068 },
  { "id": "mango-markets", "date": "12-11-2022", "usd": 0.0129904397 },
  { "id": "mango-markets", "date": "11-11-2022", "usd": 0.0118704267 },
  { "id": "mango-markets", "date": "10-11-2022", "usd": 0.0114190169 },
  { "id": "mango-markets", "date": "09-11-2022", "usd": 0.0129559125 },
  { "id": "mango-markets", "date": "08-11-2022", "usd": 0.0160527265 },
  { "id": "mango-markets", "date": "07-11-2022", "usd": 0.0164039514 },
  { "id": "mango-markets", "date": "06-11-2022", "usd": 0.0195840884 },
  { "id": "mango-markets", "date": "05-11-2022", "usd": 0.0168990642 },
  { "id": "mango-markets", "date": "04-11-2022", "usd": 0.0163355456 },
  { "id": "mango-markets", "date": "03-11-2022", "usd": 0.0164353466 },
  { "id": "mango-markets", "date": "02-11-2022", "usd": 0.016115264 },
  { "id": "mango-markets", "date": "01-11-2022", "usd": 0.0160721141 },
  { "id": "mango-markets", "date": "31-10-2022", "usd": 0.0156652128 },
  { "id": "mango-markets", "date": "30-10-2022", "usd": 0.0173563841 },
  { "id": "mango-markets", "date": "29-10-2022", "usd": 0.0175118793 },
  { "id": "mango-markets", "date": "28-10-2022", "usd": 0.0174706686 },
  { "id": "mango-markets", "date": "27-10-2022", "usd": 0.0177318026 },
  { "id": "mango-markets", "date": "26-10-2022", "usd": 0.0181797599 },
  { "id": "mango-markets", "date": "25-10-2022", "usd": 0.0179139515 },
  { "id": "mango-markets", "date": "24-10-2022", "usd": 0.0188222572 },
  { "id": "mango-markets", "date": "23-10-2022", "usd": 0.017857597 },
  { "id": "mango-markets", "date": "22-10-2022", "usd": 0.0214877392 },
  { "id": "mango-markets", "date": "21-10-2022", "usd": 0.0216495662 },
  { "id": "mango-markets", "date": "20-10-2022", "usd": 0.0212170655 },
  { "id": "mango-markets", "date": "19-10-2022", "usd": 0.0210680618 },
  { "id": "mango-markets", "date": "18-10-2022", "usd": 0.0239605111 },
  { "id": "mango-markets", "date": "17-10-2022", "usd": 0.0236082366 },
  { "id": "mango-markets", "date": "16-10-2022", "usd": 0.0243375701 },
  { "id": "mango-markets", "date": "15-10-2022", "usd": 0.0257568401 },
  { "id": "mango-markets", "date": "14-10-2022", "usd": 0.0247801348 },
  { "id": "mango-markets", "date": "13-10-2022", "usd": 0.0234856685 },
  { "id": "mango-markets", "date": "12-10-2022", "usd": 0.0249715348 },
  { "id": "mango-markets", "date": "11-10-2022", "usd": 0.0400741719 },
  { "id": "mango-markets", "date": "10-10-2022", "usd": 0.0407128659 },
  { "id": "mango-markets", "date": "09-10-2022", "usd": 0.0406668857 },
  { "id": "mango-markets", "date": "08-10-2022", "usd": 0.0410140994 },
  { "id": "mango-markets", "date": "07-10-2022", "usd": 0.0413763891 },
  { "id": "mango-markets", "date": "06-10-2022", "usd": 0.0419521543 },
  { "id": "mango-markets", "date": "05-10-2022", "usd": 0.041605943 },
  { "id": "mango-markets", "date": "04-10-2022", "usd": 0.041844899 },
  { "id": "mango-markets", "date": "03-10-2022", "usd": 0.0413941294 },
  { "id": "mango-markets", "date": "02-10-2022", "usd": 0.0420565201 },
  { "id": "mango-markets", "date": "01-10-2022", "usd": 0.0425839126 },
  { "id": "mango-markets", "date": "30-09-2022", "usd": 0.042327116 },
  { "id": "mango-markets", "date": "29-09-2022", "usd": 0.0426770389 },
  { "id": "mango-markets", "date": "28-09-2022", "usd": 0.0419491712 },
  { "id": "mango-markets", "date": "27-09-2022", "usd": 0.0427274853 },
  { "id": "mango-markets", "date": "26-09-2022", "usd": 0.0417448027 },
  { "id": "mango-markets", "date": "25-09-2022", "usd": 0.0415032342 },
  { "id": "mango-markets", "date": "24-09-2022", "usd": 0.0414311314 },
  { "id": "mango-markets", "date": "23-09-2022", "usd": 0.0415510698 },
  { "id": "mango-markets", "date": "22-09-2022", "usd": 0.0410563466 },
  { "id": "mango-markets", "date": "21-09-2022", "usd": 0.0415910333 },
  { "id": "mango-markets", "date": "20-09-2022", "usd": 0.0415452373 },
  { "id": "mango-markets", "date": "19-09-2022", "usd": 0.0410780509 },
  { "id": "mango-markets", "date": "18-09-2022", "usd": 0.0420900942 },
  { "id": "mango-markets", "date": "17-09-2022", "usd": 0.0417621535 },
  { "id": "mango-markets", "date": "16-09-2022", "usd": 0.0419355873 },
  { "id": "mango-markets", "date": "15-09-2022", "usd": 0.0420140937 },
  { "id": "mango-markets", "date": "14-09-2022", "usd": 0.0425363618 },
  { "id": "mango-markets", "date": "13-09-2022", "usd": 0.0436832993 },
  { "id": "mango-markets", "date": "12-09-2022", "usd": 0.0442845336 },
  { "id": "mango-markets", "date": "11-09-2022", "usd": 0.0454447799 },
  { "id": "mango-markets", "date": "10-09-2022", "usd": 0.0455056872 },
  { "id": "mango-markets", "date": "09-09-2022", "usd": 0.0459151861 },
  { "id": "mango-markets", "date": "08-09-2022", "usd": 0.0456900008 },
  { "id": "mango-markets", "date": "07-09-2022", "usd": 0.0451085824 },
  { "id": "mango-markets", "date": "06-09-2022", "usd": 0.0458521972 },
  { "id": "mango-markets", "date": "05-09-2022", "usd": 0.0454932056 },
  { "id": "mango-markets", "date": "04-09-2022", "usd": 0.0452744793 },
  { "id": "mango-markets", "date": "03-09-2022", "usd": 0.0451622248 },
  { "id": "mango-markets", "date": "02-09-2022", "usd": 0.0449527522 },
  { "id": "mango-markets", "date": "01-09-2022", "usd": 0.0442639722 },
  { "id": "mango-markets", "date": "31-08-2022", "usd": 0.0447894935 },
  { "id": "mango-markets", "date": "30-08-2022", "usd": 0.0445504884 },
  { "id": "mango-markets", "date": "29-08-2022", "usd": 0.0433958738 },
  { "id": "mango-markets", "date": "28-08-2022", "usd": 0.0438029413 },
  { "id": "mango-markets", "date": "27-08-2022", "usd": 0.0439612892 },
  { "id": "mango-markets", "date": "26-08-2022", "usd": 0.045083008 },
  { "id": "mango-markets", "date": "25-08-2022", "usd": 0.0457994342 },
  { "id": "mango-markets", "date": "24-08-2022", "usd": 0.0455177471 },
  { "id": "mango-markets", "date": "23-08-2022", "usd": 0.0463531598 },
  { "id": "mango-markets", "date": "22-08-2022", "usd": 0.0454756971 },
  { "id": "mango-markets", "date": "21-08-2022", "usd": 0.0474393137 },
  { "id": "mango-markets", "date": "20-08-2022", "usd": 0.0478705121 },
  { "id": "mango-markets", "date": "19-08-2022", "usd": 0.0488757391 },
  { "id": "mango-markets", "date": "18-08-2022", "usd": 0.0490195283 },
  { "id": "mango-markets", "date": "17-08-2022", "usd": 0.0497894176 },
  { "id": "mango-markets", "date": "16-08-2022", "usd": 0.0493368093 },
  { "id": "mango-markets", "date": "15-08-2022", "usd": 0.0502203352 },
  { "id": "mango-markets", "date": "14-08-2022", "usd": 0.0508229424 },
  { "id": "mango-markets", "date": "13-08-2022", "usd": 0.0505695102 },
  { "id": "mango-markets", "date": "12-08-2022", "usd": 0.0498484877 },
  { "id": "mango-markets", "date": "11-08-2022", "usd": 0.0529123236 },
  { "id": "mango-markets", "date": "10-08-2022", "usd": 0.0511634157 },
  { "id": "mango-markets", "date": "09-08-2022", "usd": 0.0504003431 },
  { "id": "mango-markets", "date": "08-08-2022", "usd": 0.0499260034 },
  { "id": "mango-markets", "date": "07-08-2022", "usd": 0.0483516253 },
  { "id": "mango-markets", "date": "06-08-2022", "usd": 0.0486509132 },
  { "id": "mango-markets", "date": "05-08-2022", "usd": 0.04830902 },
  { "id": "mango-markets", "date": "04-08-2022", "usd": 0.047995104 },
  { "id": "mango-markets", "date": "03-08-2022", "usd": 0.0480647831 },
  { "id": "mango-markets", "date": "02-08-2022", "usd": 0.0482910994 },
  { "id": "mango-markets", "date": "01-08-2022", "usd": 0.0495978936 },
  { "id": "mango-markets", "date": "31-07-2022", "usd": 0.0497752166 },
  { "id": "mango-markets", "date": "30-07-2022", "usd": 0.049394553 },
  { "id": "mango-markets", "date": "29-07-2022", "usd": 0.0500859996 },
  { "id": "mango-markets", "date": "28-07-2022", "usd": 0.0480523872 },
  { "id": "mango-markets", "date": "27-07-2022", "usd": 0.0452870822 },
  { "id": "mango-markets", "date": "26-07-2022", "usd": 0.0446558689 },
  { "id": "mango-markets", "date": "25-07-2022", "usd": 0.0463054157 },
  { "id": "mango-markets", "date": "24-07-2022", "usd": 0.046978127 },
  { "id": "mango-markets", "date": "23-07-2022", "usd": 0.0474134751 },
  { "id": "mango-markets", "date": "22-07-2022", "usd": 0.0476598601 },
  { "id": "mango-markets", "date": "21-07-2022", "usd": 0.0469380876 },
  { "id": "mango-markets", "date": "20-07-2022", "usd": 0.0487010401 },
  { "id": "mango-markets", "date": "19-07-2022", "usd": 0.0474980492 },
  { "id": "mango-markets", "date": "18-07-2022", "usd": 0.0457350648 },
  { "id": "mango-markets", "date": "17-07-2022", "usd": 0.0458014325 },
  { "id": "mango-markets", "date": "16-07-2022", "usd": 0.0441117175 },
  { "id": "mango-markets", "date": "15-07-2022", "usd": 0.0445883373 },
  { "id": "mango-markets", "date": "14-07-2022", "usd": 0.043410518 },
  { "id": "mango-markets", "date": "13-07-2022", "usd": 0.0432499105 },
  { "id": "mango-markets", "date": "12-07-2022", "usd": 0.0437157801 },
  { "id": "mango-markets", "date": "11-07-2022", "usd": 0.0447879644 },
  { "id": "mango-markets", "date": "10-07-2022", "usd": 0.0465390708 },
  { "id": "mango-markets", "date": "09-07-2022", "usd": 0.047154323 },
  { "id": "mango-markets", "date": "08-07-2022", "usd": 0.0472328288 },
  { "id": "mango-markets", "date": "07-07-2022", "usd": 0.0463482026 },
  { "id": "mango-markets", "date": "06-07-2022", "usd": 0.0467974329 },
  { "id": "mango-markets", "date": "05-07-2022", "usd": 0.0472087292 },
  { "id": "mango-markets", "date": "04-07-2022", "usd": 0.0471631399 },
  { "id": "mango-markets", "date": "03-07-2022", "usd": 0.0475160419 },
  { "id": "mango-markets", "date": "02-07-2022", "usd": 0.0477598744 },
  { "id": "mango-markets", "date": "01-07-2022", "usd": 0.047943216 },
  { "id": "mango-markets", "date": "30-06-2022", "usd": 0.0497626508 },
  { "id": "mango-markets", "date": "29-06-2022", "usd": 0.0505801512 },
  { "id": "mango-markets", "date": "28-06-2022", "usd": 0.0516804439 },
  { "id": "mango-markets", "date": "27-06-2022", "usd": 0.0520966286 },
  { "id": "mango-markets", "date": "26-06-2022", "usd": 0.0526151754 },
  { "id": "mango-markets", "date": "25-06-2022", "usd": 0.0525430169 },
  { "id": "mango-markets", "date": "24-06-2022", "usd": 0.0518225094 },
  { "id": "mango-markets", "date": "23-06-2022", "usd": 0.0512330309 },
  { "id": "mango-markets", "date": "22-06-2022", "usd": 0.051064402 },
  { "id": "mango-markets", "date": "21-06-2022", "usd": 0.0536578527 },
  { "id": "mango-markets", "date": "20-06-2022", "usd": 0.0493524847 },
  { "id": "mango-markets", "date": "19-06-2022", "usd": 0.0480419402 },
  { "id": "mango-markets", "date": "18-06-2022", "usd": 0.0477698613 },
  { "id": "mango-markets", "date": "17-06-2022", "usd": 0.0468569858 },
  { "id": "mango-markets", "date": "16-06-2022", "usd": 0.0448761271 },
  { "id": "mango-markets", "date": "15-06-2022", "usd": 0.0403290825 },
  { "id": "mango-markets", "date": "14-06-2022", "usd": 0.0442148927 },
  { "id": "mango-markets", "date": "13-06-2022", "usd": 0.0451303503 },
  { "id": "mango-markets", "date": "12-06-2022", "usd": 0.0476370445 },
  { "id": "mango-markets", "date": "11-06-2022", "usd": 0.0496796954 },
  { "id": "mango-markets", "date": "10-06-2022", "usd": 0.0518172161 },
  { "id": "mango-markets", "date": "09-06-2022", "usd": 0.0535432724 },
  { "id": "mango-markets", "date": "08-06-2022", "usd": 0.0521700258 },
  { "id": "mango-markets", "date": "07-06-2022", "usd": 0.0525815583 },
  { "id": "mango-markets", "date": "06-06-2022", "usd": 0.0562245788 },
  { "id": "mango-markets", "date": "05-06-2022", "usd": 0.0548086535 },
  { "id": "mango-markets", "date": "04-06-2022", "usd": 0.0545598831 },
  { "id": "mango-markets", "date": "03-06-2022", "usd": 0.0549063206 },
  { "id": "mango-markets", "date": "02-06-2022", "usd": 0.0553092184 },
  { "id": "mango-markets", "date": "01-06-2022", "usd": 0.0565878201 },
  { "id": "mango-markets", "date": "31-05-2022", "usd": 0.0586767815 },
  { "id": "mango-markets", "date": "30-05-2022", "usd": 0.0576448642 },
  { "id": "mango-markets", "date": "29-05-2022", "usd": 0.055787634 },
  { "id": "mango-markets", "date": "28-05-2022", "usd": 0.0558754996 },
  { "id": "mango-markets", "date": "27-05-2022", "usd": 0.0562691665 },
  { "id": "mango-markets", "date": "26-05-2022", "usd": 0.0589267774 },
  { "id": "mango-markets", "date": "25-05-2022", "usd": 0.0617880778 },
  { "id": "mango-markets", "date": "24-05-2022", "usd": 0.0626695561 },
  { "id": "mango-markets", "date": "23-05-2022", "usd": 0.0645066877 },
  { "id": "mango-markets", "date": "22-05-2022", "usd": 0.0649381235 },
  { "id": "mango-markets", "date": "21-05-2022", "usd": 0.0659021401 },
  { "id": "mango-markets", "date": "20-05-2022", "usd": 0.0697451028 },
  { "id": "mango-markets", "date": "19-05-2022", "usd": 0.0678083224 },
  { "id": "mango-markets", "date": "18-05-2022", "usd": 0.0689304009 },
  { "id": "mango-markets", "date": "17-05-2022", "usd": 0.0691532071 },
  { "id": "mango-markets", "date": "16-05-2022", "usd": 0.0684569039 },
  { "id": "mango-markets", "date": "15-05-2022", "usd": 0.0687816253 },
  { "id": "mango-markets", "date": "14-05-2022", "usd": 0.0713021561 },
  { "id": "mango-markets", "date": "13-05-2022", "usd": 0.0721858627 },
  { "id": "mango-markets", "date": "12-05-2022", "usd": 0.0733099572 },
  { "id": "mango-markets", "date": "11-05-2022", "usd": 0.0862173819 },
  { "id": "mango-markets", "date": "10-05-2022", "usd": 0.0873171217 },
  { "id": "mango-markets", "date": "09-05-2022", "usd": 0.0933245016 },
  { "id": "mango-markets", "date": "08-05-2022", "usd": 0.0966732923 },
  { "id": "mango-markets", "date": "07-05-2022", "usd": 0.099607389 },
  { "id": "mango-markets", "date": "06-05-2022", "usd": 0.1041380059 },
  { "id": "mango-markets", "date": "05-05-2022", "usd": 0.1097494735 },
  { "id": "mango-markets", "date": "04-05-2022", "usd": 0.1081724189 },
  { "id": "mango-markets", "date": "03-05-2022", "usd": 0.1122381966 },
  { "id": "mango-markets", "date": "02-05-2022", "usd": 0.1143711239 },
  { "id": "mango-markets", "date": "01-05-2022", "usd": 0.1141397569 },
  { "id": "mango-markets", "date": "30-04-2022", "usd": 0.1186752179 },
  { "id": "mango-markets", "date": "29-04-2022", "usd": 0.1219018139 },
  { "id": "mango-markets", "date": "28-04-2022", "usd": 0.1269859272 },
  { "id": "mango-markets", "date": "27-04-2022", "usd": 0.1230845995 },
  { "id": "mango-markets", "date": "26-04-2022", "usd": 0.1429609529 },
  { "id": "mango-markets", "date": "25-04-2022", "usd": 0.1349736397 },
  { "id": "mango-markets", "date": "24-04-2022", "usd": 0.1390102501 },
  { "id": "mango-markets", "date": "23-04-2022", "usd": 0.1372375257 },
  { "id": "mango-markets", "date": "22-04-2022", "usd": 0.1391519688 },
  { "id": "mango-markets", "date": "21-04-2022", "usd": 0.140384703 },
  { "id": "mango-markets", "date": "20-04-2022", "usd": 0.1407886751 },
  { "id": "mango-markets", "date": "19-04-2022", "usd": 0.1413103901 },
  { "id": "mango-markets", "date": "18-04-2022", "usd": 0.1412263162 },
  { "id": "mango-markets", "date": "17-04-2022", "usd": 0.1432515017 },
  { "id": "mango-markets", "date": "16-04-2022", "usd": 0.1430770545 },
  { "id": "mango-markets", "date": "15-04-2022", "usd": 0.1446731609 },
  { "id": "mango-markets", "date": "14-04-2022", "usd": 0.1511297536 },
  { "id": "mango-markets", "date": "13-04-2022", "usd": 0.1520255736 },
  { "id": "mango-markets", "date": "12-04-2022", "usd": 0.1511396481 },
  { "id": "mango-markets", "date": "11-04-2022", "usd": 0.1506567027 },
  { "id": "mango-markets", "date": "10-04-2022", "usd": 0.1536078063 },
  { "id": "mango-markets", "date": "09-04-2022", "usd": 0.1537518892 },
  { "id": "mango-markets", "date": "08-04-2022", "usd": 0.1534689058 },
  { "id": "mango-markets", "date": "07-04-2022", "usd": 0.1572292665 },
  { "id": "mango-markets", "date": "06-04-2022", "usd": 0.1577766602 },
  { "id": "mango-markets", "date": "05-04-2022", "usd": 0.1606981924 },
  { "id": "mango-markets", "date": "04-04-2022", "usd": 0.1646718421 },
  { "id": "mango-markets", "date": "03-04-2022", "usd": 0.165555497 },
  { "id": "mango-markets", "date": "02-04-2022", "usd": 0.1657696219 },
  { "id": "mango-markets", "date": "01-04-2022", "usd": 0.1681750383 },
  { "id": "mango-markets", "date": "31-03-2022", "usd": 0.1645151231 },
  { "id": "mango-markets", "date": "30-03-2022", "usd": 0.1711982211 },
  { "id": "mango-markets", "date": "29-03-2022", "usd": 0.1672318832 },
  { "id": "mango-markets", "date": "28-03-2022", "usd": 0.1661664277 },
  { "id": "mango-markets", "date": "27-03-2022", "usd": 0.1580095117 },
  { "id": "mango-markets", "date": "26-03-2022", "usd": 0.1540358123 },
  { "id": "mango-markets", "date": "25-03-2022", "usd": 0.1544350782 },
  { "id": "mango-markets", "date": "24-03-2022", "usd": 0.1568298856 },
  { "id": "mango-markets", "date": "23-03-2022", "usd": 0.1558919384 },
  { "id": "mango-markets", "date": "22-03-2022", "usd": 0.1521948059 },
  { "id": "mango-markets", "date": "21-03-2022", "usd": 0.1542434907 },
  { "id": "mango-markets", "date": "20-03-2022", "usd": 0.1515409213 },
  { "id": "mango-markets", "date": "19-03-2022", "usd": 0.1582674299 },
  { "id": "mango-markets", "date": "18-03-2022", "usd": 0.1502543863 },
  { "id": "mango-markets", "date": "17-03-2022", "usd": 0.1504325214 },
  { "id": "mango-markets", "date": "16-03-2022", "usd": 0.1502939977 },
  { "id": "mango-markets", "date": "15-03-2022", "usd": 0.1457209321 },
  { "id": "mango-markets", "date": "14-03-2022", "usd": 0.1511938468 },
  { "id": "mango-markets", "date": "13-03-2022", "usd": 0.1490583442 },
  { "id": "mango-markets", "date": "12-03-2022", "usd": 0.1515131244 },
  { "id": "mango-markets", "date": "11-03-2022", "usd": 0.1519695418 },
  { "id": "mango-markets", "date": "10-03-2022", "usd": 0.1564040734 },
  { "id": "mango-markets", "date": "09-03-2022", "usd": 0.1526617382 },
  { "id": "mango-markets", "date": "08-03-2022", "usd": 0.1527274299 },
  { "id": "mango-markets", "date": "07-03-2022", "usd": 0.1500613655 },
  { "id": "mango-markets", "date": "06-03-2022", "usd": 0.1480961841 },
  { "id": "mango-markets", "date": "05-03-2022", "usd": 0.1597371757 },
  { "id": "mango-markets", "date": "04-03-2022", "usd": 0.1587909335 },
  { "id": "mango-markets", "date": "03-03-2022", "usd": 0.1597873111 },
  { "id": "mango-markets", "date": "02-03-2022", "usd": 0.1623962542 },
  { "id": "mango-markets", "date": "01-03-2022", "usd": 0.158638538 },
  { "id": "mango-markets", "date": "28-02-2022", "usd": 0.1545082712 },
  { "id": "mango-markets", "date": "27-02-2022", "usd": 0.152020841 },
  { "id": "mango-markets", "date": "26-02-2022", "usd": 0.1528442582 },
  { "id": "mango-markets", "date": "25-02-2022", "usd": 0.1521671057 },
  { "id": "mango-markets", "date": "24-02-2022", "usd": 0.147993755 },
  { "id": "mango-markets", "date": "23-02-2022", "usd": 0.1525553886 },
  { "id": "mango-markets", "date": "22-02-2022", "usd": 0.1492697685 },
  { "id": "mango-markets", "date": "21-02-2022", "usd": 0.1573014175 },
  { "id": "mango-markets", "date": "20-02-2022", "usd": 0.169162459 },
  { "id": "mango-markets", "date": "19-02-2022", "usd": 0.1721454211 },
  { "id": "mango-markets", "date": "18-02-2022", "usd": 0.1729163258 },
  { "id": "mango-markets", "date": "17-02-2022", "usd": 0.1706061692 },
  { "id": "mango-markets", "date": "16-02-2022", "usd": 0.180932241 },
  { "id": "mango-markets", "date": "15-02-2022", "usd": 0.1835816973 },
  { "id": "mango-markets", "date": "14-02-2022", "usd": 0.178415454 },
  { "id": "mango-markets", "date": "13-02-2022", "usd": 0.1768548201 },
  { "id": "mango-markets", "date": "12-02-2022", "usd": 0.1683435004 },
  { "id": "mango-markets", "date": "11-02-2022", "usd": 0.1727463516 },
  { "id": "mango-markets", "date": "10-02-2022", "usd": 0.1782670654 },
  { "id": "mango-markets", "date": "09-02-2022", "usd": 0.1775150999 },
  { "id": "mango-markets", "date": "08-02-2022", "usd": 0.1664630757 },
  { "id": "mango-markets", "date": "07-02-2022", "usd": 0.1732217864 },
  { "id": "mango-markets", "date": "06-02-2022", "usd": 0.1625753708 },
  { "id": "mango-markets", "date": "05-02-2022", "usd": 0.1588957619 },
  { "id": "mango-markets", "date": "04-02-2022", "usd": 0.151479088 },
  { "id": "mango-markets", "date": "03-02-2022", "usd": 0.1436951783 },
  { "id": "mango-markets", "date": "02-02-2022", "usd": 0.1474313481 },
  { "id": "mango-markets", "date": "01-02-2022", "usd": 0.156508059 },
  { "id": "mango-markets", "date": "31-01-2022", "usd": 0.1488660999 },
  { "id": "mango-markets", "date": "30-01-2022", "usd": 0.1519174668 },
  { "id": "mango-markets", "date": "29-01-2022", "usd": 0.1527860445 },
  { "id": "mango-markets", "date": "28-01-2022", "usd": 0.1471596736 },
  { "id": "mango-markets", "date": "27-01-2022", "usd": 0.1529828393 },
  { "id": "mango-markets", "date": "26-01-2022", "usd": 0.1524046736 },
  { "id": "mango-markets", "date": "25-01-2022", "usd": 0.1539224017 },
  { "id": "mango-markets", "date": "24-01-2022", "usd": 0.1504631016 },
  { "id": "mango-markets", "date": "23-01-2022", "usd": 0.1583567985 },
  { "id": "mango-markets", "date": "22-01-2022", "usd": 0.1589864319 },
  { "id": "mango-markets", "date": "21-01-2022", "usd": 0.1827571989 },
  { "id": "mango-markets", "date": "20-01-2022", "usd": 0.2048095536 },
  { "id": "mango-markets", "date": "19-01-2022", "usd": 0.2000835304 },
  { "id": "mango-markets", "date": "18-01-2022", "usd": 0.2026168573 },
  { "id": "mango-markets", "date": "17-01-2022", "usd": 0.1986681744 },
  { "id": "mango-markets", "date": "16-01-2022", "usd": 0.1989467181 },
  { "id": "mango-markets", "date": "15-01-2022", "usd": 0.1956546068 },
  { "id": "mango-markets", "date": "14-01-2022", "usd": 0.1986149872 },
  { "id": "mango-markets", "date": "13-01-2022", "usd": 0.1984956746 },
  { "id": "mango-markets", "date": "12-01-2022", "usd": 0.2108773962 },
  { "id": "mango-markets", "date": "11-01-2022", "usd": 0.2083036938 },
  { "id": "mango-markets", "date": "10-01-2022", "usd": 0.1958245994 },
  { "id": "mango-markets", "date": "09-01-2022", "usd": 0.1933845201 },
  { "id": "mango-markets", "date": "08-01-2022", "usd": 0.1882888827 },
  { "id": "mango-markets", "date": "07-01-2022", "usd": 0.1919651409 },
  { "id": "mango-markets", "date": "06-01-2022", "usd": 0.2111860795 },
  { "id": "mango-markets", "date": "05-01-2022", "usd": 0.2208117166 },
  { "id": "mango-markets", "date": "04-01-2022", "usd": 0.2342817334 },
  { "id": "mango-markets", "date": "03-01-2022", "usd": 0.2172807771 },
  { "id": "mango-markets", "date": "02-01-2022", "usd": 0.2118694661 },
  { "id": "mango-markets", "date": "01-01-2022", "usd": 0.217146 },
  { "id": "mango-markets", "date": "31-12-2021", "usd": 0.206004179 },
  { "id": "mango-markets", "date": "30-12-2021", "usd": 0.2138648943 },
  { "id": "mango-markets", "date": "29-12-2021", "usd": 0.2149773437 },
  { "id": "mango-markets", "date": "28-12-2021", "usd": 0.2431555346 },
  { "id": "mango-markets", "date": "27-12-2021", "usd": 0.2605229878 },
  { "id": "mango-markets", "date": "26-12-2021", "usd": 0.2701943239 },
  { "id": "mango-markets", "date": "25-12-2021", "usd": 0.2854483395 },
  { "id": "mango-markets", "date": "24-12-2021", "usd": 0.247997944 },
  { "id": "mango-markets", "date": "23-12-2021", "usd": 0.2229566223 },
  { "id": "mango-markets", "date": "22-12-2021", "usd": 0.1967377721 },
  { "id": "mango-markets", "date": "21-12-2021", "usd": 0.1911376615 },
  { "id": "mango-markets", "date": "20-12-2021", "usd": 0.1835100619 },
  { "id": "mango-markets", "date": "19-12-2021", "usd": 0.188188868 },
  { "id": "mango-markets", "date": "18-12-2021", "usd": 0.1914581247 },
  { "id": "mango-markets", "date": "17-12-2021", "usd": 0.1918417588 },
  { "id": "mango-markets", "date": "16-12-2021", "usd": 0.1937491532 },
  { "id": "mango-markets", "date": "15-12-2021", "usd": 0.2011378194 },
  { "id": "mango-markets", "date": "14-12-2021", "usd": 0.193370633 },
  { "id": "mango-markets", "date": "13-12-2021", "usd": 0.193758766 },
  { "id": "mango-markets", "date": "12-12-2021", "usd": 0.2245233149 },
  { "id": "mango-markets", "date": "11-12-2021", "usd": 0.2270280574 },
  { "id": "mango-markets", "date": "10-12-2021", "usd": 0.2232604521 },
  { "id": "mango-markets", "date": "09-12-2021", "usd": 0.2527121868 },
  { "id": "mango-markets", "date": "08-12-2021", "usd": 0.2612219913 },
  { "id": "mango-markets", "date": "07-12-2021", "usd": 0.2596750954 },
  { "id": "mango-markets", "date": "06-12-2021", "usd": 0.2597267128 },
  { "id": "mango-markets", "date": "05-12-2021", "usd": 0.2573419169 },
  { "id": "mango-markets", "date": "04-12-2021", "usd": 0.2703105216 },
  { "id": "mango-markets", "date": "03-12-2021", "usd": 0.3005000585 },
  { "id": "mango-markets", "date": "02-12-2021", "usd": 0.3141468811 },
  { "id": "mango-markets", "date": "01-12-2021", "usd": 0.3123392877 },
  { "id": "mango-markets", "date": "30-11-2021", "usd": 0.2996311741 },
  { "id": "mango-markets", "date": "29-11-2021", "usd": 0.317051637 },
  { "id": "mango-markets", "date": "28-11-2021", "usd": 0.2839672363 },
  { "id": "mango-markets", "date": "27-11-2021", "usd": 0.2861935352 },
  { "id": "mango-markets", "date": "26-11-2021", "usd": 0.2904285125 },
  { "id": "mango-markets", "date": "25-11-2021", "usd": 0.3116586851 },
  { "id": "mango-markets", "date": "24-11-2021", "usd": 0.2986597432 },
  { "id": "mango-markets", "date": "23-11-2021", "usd": 0.3181548674 },
  { "id": "mango-markets", "date": "22-11-2021", "usd": 0.3089565614 },
  { "id": "mango-markets", "date": "21-11-2021", "usd": 0.3214093071 },
  { "id": "mango-markets", "date": "20-11-2021", "usd": 0.3248265242 },
  { "id": "mango-markets", "date": "19-11-2021", "usd": 0.3293393045 },
  { "id": "mango-markets", "date": "18-11-2021", "usd": 0.3082100945 },
  { "id": "mango-markets", "date": "17-11-2021", "usd": 0.3280959819 },
  { "id": "mango-markets", "date": "16-11-2021", "usd": 0.3461108818 },
  { "id": "mango-markets", "date": "15-11-2021", "usd": 0.3817173523 },
  { "id": "mango-markets", "date": "14-11-2021", "usd": 0.3588802026 },
  { "id": "mango-markets", "date": "13-11-2021", "usd": 0.3593166885 },
  { "id": "mango-markets", "date": "12-11-2021", "usd": 0.3601572911 },
  { "id": "mango-markets", "date": "11-11-2021", "usd": 0.3737138568 },
  { "id": "mango-markets", "date": "10-11-2021", "usd": 0.3703285526 },
  { "id": "mango-markets", "date": "09-11-2021", "usd": 0.3893422714 },
  { "id": "mango-markets", "date": "08-11-2021", "usd": 0.4216895647 },
  { "id": "mango-markets", "date": "07-11-2021", "usd": 0.4036728534 },
  { "id": "mango-markets", "date": "06-11-2021", "usd": 0.4248916213 },
  { "id": "mango-markets", "date": "05-11-2021", "usd": 0.3760094756 },
  { "id": "mango-markets", "date": "04-11-2021", "usd": 0.3864634804 },
  { "id": "mango-markets", "date": "03-11-2021", "usd": 0.3816697572 },
  { "id": "mango-markets", "date": "02-11-2021", "usd": 0.2987856435 },
  { "id": "mango-markets", "date": "01-11-2021", "usd": 0.294905968 },
  { "id": "mango-markets", "date": "31-10-2021", "usd": 0.2894654837 },
  { "id": "mango-markets", "date": "30-10-2021", "usd": 0.2937356316 },
  { "id": "mango-markets", "date": "29-10-2021", "usd": 0.290781714 },
  { "id": "mango-markets", "date": "28-10-2021", "usd": 0.2741941486 },
  { "id": "mango-markets", "date": "27-10-2021", "usd": 0.2645624705 },
  { "id": "mango-markets", "date": "26-10-2021", "usd": 0.2954345077 },
  { "id": "mango-markets", "date": "25-10-2021", "usd": 0.2629303649 },
  { "id": "mango-markets", "date": "24-10-2021", "usd": 0.2530271333 },
  { "id": "mango-markets", "date": "23-10-2021", "usd": 0.2528863898 },
  { "id": "mango-markets", "date": "22-10-2021", "usd": 0.2560687678 },
  { "id": "mango-markets", "date": "21-10-2021", "usd": 0.266530016 },
  { "id": "mango-markets", "date": "20-10-2021", "usd": 0.2677931153 },
  { "id": "mango-markets", "date": "19-10-2021", "usd": 0.2409916335 },
  { "id": "mango-markets", "date": "18-10-2021", "usd": 0.247989805 },
  { "id": "mango-markets", "date": "17-10-2021", "usd": 0.2643134585 },
  { "id": "mango-markets", "date": "16-10-2021", "usd": 0.2639308085 },
  { "id": "mango-markets", "date": "15-10-2021", "usd": 0.2764592995 },
  { "id": "mango-markets", "date": "14-10-2021", "usd": 0.2664979557 },
  { "id": "mango-markets", "date": "13-10-2021", "usd": 0.2707350902 },
  { "id": "mango-markets", "date": "12-10-2021", "usd": 0.2636710999 },
  { "id": "mango-markets", "date": "11-10-2021", "usd": 0.2705386457 },
  { "id": "mango-markets", "date": "10-10-2021", "usd": 0.2752496294 },
  { "id": "mango-markets", "date": "09-10-2021", "usd": 0.2820616737 },
  { "id": "mango-markets", "date": "08-10-2021", "usd": 0.2828841937 },
  { "id": "mango-markets", "date": "07-10-2021", "usd": 0.3055592806 },
  { "id": "mango-markets", "date": "06-10-2021", "usd": 0.3184339986 },
  { "id": "mango-markets", "date": "05-10-2021", "usd": 0.3356124463 },
  { "id": "mango-markets", "date": "04-10-2021", "usd": 0.3373830291 },
  { "id": "mango-markets", "date": "03-10-2021", "usd": 0.3409556268 },
  { "id": "mango-markets", "date": "02-10-2021", "usd": 0.358360566 },
  { "id": "mango-markets", "date": "01-10-2021", "usd": 0.3464379056 },
  { "id": "mango-markets", "date": "30-09-2021", "usd": 0.3220269242 },
  { "id": "mango-markets", "date": "29-09-2021", "usd": 0.3034400354 },
  { "id": "mango-markets", "date": "28-09-2021", "usd": 0.3074842659 },
  { "id": "mango-markets", "date": "27-09-2021", "usd": 0.335740162 },
  { "id": "mango-markets", "date": "26-09-2021", "usd": 0.2979823087 },
  { "id": "mango-markets", "date": "25-09-2021", "usd": 0.273773568 },
  { "id": "mango-markets", "date": "24-09-2021", "usd": 0.2853733084 },
  { "id": "mango-markets", "date": "23-09-2021", "usd": 0.3002204713 },
  { "id": "mango-markets", "date": "22-09-2021", "usd": 0.2794319296 },
  { "id": "mango-markets", "date": "21-09-2021", "usd": 0.251276085 },
  { "id": "mango-markets", "date": "20-09-2021", "usd": 0.2821619177 },
  { "id": "mango-markets", "date": "19-09-2021", "usd": 0.3348157522 },
  { "id": "mango-markets", "date": "18-09-2021", "usd": 0.3479725798 },
  { "id": "mango-markets", "date": "17-09-2021", "usd": 0.3302475 },
  { "id": "mango-markets", "date": "16-09-2021", "usd": 0.3766996119 },
  { "id": "mango-markets", "date": "15-09-2021", "usd": 0.3583184012 },
  { "id": "mango-markets", "date": "14-09-2021", "usd": 0.353845809 },
  { "id": "mango-markets", "date": "13-09-2021", "usd": 0.4031174856 },
  { "id": "mango-markets", "date": "12-09-2021", "usd": 0.41386261 },
  { "id": "mango-markets", "date": "11-09-2021", "usd": 0.44567056 },
  { "id": "mango-markets", "date": "10-09-2021", "usd": 0.39912456 },
  { "id": "mango-markets", "date": "09-09-2021", "usd": 0.45310252 },
  { "id": "mango-markets", "date": "08-09-2021", "usd": 0.39420093 },
  { "id": "mango-markets", "date": "07-09-2021", "usd": 0.37999894 },
  { "id": "mango-markets", "date": "06-09-2021", "usd": 0.41777455 },
  { "id": "mango-markets", "date": "05-09-2021", "usd": 0.36602442 },
  { "id": "mango-markets", "date": "04-09-2021", "usd": 0.35302405 },
  { "id": "mango-markets", "date": "03-09-2021", "usd": 0.34952416 },
  { "id": "mango-markets", "date": "02-09-2021", "usd": 0.35967412 },
  { "id": "mango-markets", "date": "01-09-2021", "usd": 0.35874973 },
  { "id": "mango-markets", "date": "31-08-2021", "usd": 0.32062448 },
  { "id": "mango-markets", "date": "30-08-2021", "usd": 0.33775272 },
  { "id": "mango-markets", "date": "29-08-2021", "usd": 0.36254999 },
  { "id": "mango-markets", "date": "28-08-2021", "usd": 0.34844992 },
  { "id": "mango-markets", "date": "27-08-2021", "usd": 0.29997465 },
  { "id": "mango-markets", "date": "26-08-2021", "usd": 0.25887524 },
  { "id": "mango-markets", "date": "25-08-2021", "usd": 0.28635038 },
  { "id": "mango-markets", "date": "24-08-2021", "usd": 0.27422539 },
  { "id": "mango-markets", "date": "23-08-2021", "usd": 0.31419914 },
  { "id": "mango-markets", "date": "22-08-2021", "usd": 0.31349951 },
  { "id": "mango-markets", "date": "21-08-2021", "usd": 0.27745089 },
  { "id": "mango-markets", "date": "20-08-2021", "usd": 0.24205054 },
  { "id": "mango-markets", "date": "19-08-2021", "usd": 0.23199955 },
  { "id": "mango-markets", "date": "18-08-2021", "usd": 0.21709796 },
  { "id": "mango-markets", "date": "17-08-2021", "usd": 0.20767493 },
  { "id": "mango-markets", "date": "16-08-2021", "usd": 0.23408133 },
  { "id": "mango-markets", "date": "15-08-2021", "usd": 0.23724998 },
  { "id": "mango-markets", "date": "14-08-2021", "usd": 0.21980058 },
  { "id": "mango-markets", "date": "13-08-2021", "usd": 0.26229948 },
  { "id": "mango-markets", "date": "12-08-2021", "usd": 0.22109994 }
]
